octoapi/__init__.py
octoapi/authenticated_client.py
octoapi/electricity_meter.py
octoapi/exceptions.py
octoapi/mixins.py
octoapi/types.py
octoapi-0.1.0.dist-info/LICENSE
octoapi-0.1.0.dist-info/WHEEL
octoapi-0.1.0.dist-info/METADATA
octoapi-0.1.0.dist-info/RECORD
