Metadata-Version: 2.1
Name: octoapi
Version: 0.1.0
Summary: Python interface to Octopus Energy API
Home-page: https://github.com/jemrobinson/octoapi
License: GPLv3
Keywords: Electricity
Author: James Robinson
Author-email: james.em.robinson@gmail.com
Maintainer: James Robinson
Maintainer-email: james.em.robinson@gmail.com
Requires-Python: >=3.6,<4.0
Classifier: License :: Other/Proprietary License
Classifier: Programming Language :: Python :: 3
Classifier: Programming Language :: Python :: 3.6
Classifier: Programming Language :: Python :: 3.7
Classifier: Programming Language :: Python :: 3.8
Classifier: Programming Language :: Python :: 3.9
Requires-Dist: Sphinx (>=3.2.1,<4.0.0)
Requires-Dist: python-dateutil (>=2.8.1,<3.0.0)
Requires-Dist: pytz (>=2020.4,<2021.0)
Requires-Dist: requests (>=2.24.0,<3.0.0)
Project-URL: Repository, https://github.com/jemrobinson/octoapi
